coinbase/__init__.py
coinbase/wallet/__init__.py
coinbase/wallet/auth.py
coinbase/wallet/ca-coinbase.crt
coinbase/wallet/client.py
coinbase/wallet/coinbase-callback.pub
coinbase/wallet/compat.py
coinbase/wallet/error.py
coinbase/wallet/model.py
coinbase/wallet/util.py
coinbase-2.0.6.dist-info/DESCRIPTION.rst
coinbase-2.0.6.dist-info/METADATA
coinbase-2.0.6.dist-info/RECORD
coinbase-2.0.6.dist-info/WHEEL
coinbase-2.0.6.dist-info/metadata.json
coinbase-2.0.6.dist-info/top_level.txt
