Metadata-Version: 1.1
Name: coinbase
Version: 2.0.6
Summary: Coinbase API client library
Home-page: https://github.com/coinbase/coinbase-python/
Author: Coinbase, Inc.
Author-email: api@coinbase.com
License: MIT License
Download-URL: https://github.com/coinbase/coinbase-python/tarball/2.0.6
Keywords: api,coinbase,bitcoin,oauth2,client
Platform: UNKNOWN
Classifier: Intended Audience :: Developers
Classifier: License :: OSI Approved :: MIT License
Classifier: Operating System :: OS Independent
Classifier: Programming Language :: Python :: 2
Classifier: Programming Language :: Python :: 2.6
Classifier: Programming Language :: Python :: 2.7
Classifier: Programming Language :: Python :: 3
Classifier: Programming Language :: Python :: 3.2
Classifier: Programming Language :: Python :: 3.3
Classifier: Programming Language :: Python :: 3.4
Classifier: Programming Language :: Python
Classifier: Topic :: Software Development :: Libraries :: Python Modules
